pyfunc/__init__.py
pyfunc/__main__.py
pyfunc/errors.py
pyfunc/invoke.py
pyfunc/locate.py
pyfunc_invoker-0.1.0.dist-info/LICENSE
pyfunc_invoker-0.1.0.dist-info/METADATA
pyfunc_invoker-0.1.0.dist-info/WHEEL
pyfunc_invoker-0.1.0.dist-info/top_level.txt
pyfunc_invoker-0.1.0.dist-info/RECORD
