Metadata-Version: 2.1
Name: pyfunc-invoker
Version: 0.1.0
Summary: UNKNOWN
Home-page: UNKNOWN
License: Apache
Platform: UNKNOWN
Classifier: Programming Language :: Python :: 3
Classifier: License :: OSI Approved :: Apache Software License
Classifier: Operating System :: Unix
License-File: LICENSE
Requires-Dist: cloudevents (<2,>=1.2)
Requires-Dist: Flask (<2,>=1.0.2)
